src/__init__.py
src/git_phoenix.py
src/core/__init__.py
src/core/enums.py
src/core/exceptions.py
src/core/models.py
src/core/px_git.py
src/core/px_questionary.py
src/core/rules.py
src/core/template_methods.py
src/core/template_models.py
src/core/utils.py
src/core/actions/__init__.py
src/core/actions/block_commit.py
src/core/actions/create_branch.py
src/core/actions/custom_actions.py
src/core/actions/delete_branch.py
src/core/actions/executable.py
src/core/actions/merge.py
src/core/actions/rebase.py
src/core/actions/tag.py
src/resources/__init__.py
src/resources/phoenix-schema.json
tests/__init__.py
tests/core/__init__.py
tests/core/test_utils.py
git_phoenix-1.2.0.dist-info/LICENSE
git_phoenix-1.2.0.dist-info/METADATA
git_phoenix-1.2.0.dist-info/WHEEL
git_phoenix-1.2.0.dist-info/entry_points.txt
git_phoenix-1.2.0.dist-info/top_level.txt
git_phoenix-1.2.0.dist-info/RECORD
