Metadata-Version: 2.1
Name: git-phoenix
Version: 1.2.0
Summary: A dynamic git branching tool
Home-page: https://github.com/victoraugustofd/git-phoenix
Author: victoraugustofd
License: MIT
Platform: UNKNOWN
Requires-Python: >=3.7
License-File: LICENSE
Requires-Dist: GitPython (==3.1.24)
Requires-Dist: regex (==2021.4.4)
Requires-Dist: argparse (==1.4.0)
Requires-Dist: jsonschema (==4.0.1)
Requires-Dist: coloredlogs (==15.0.1)
Requires-Dist: questionary (==1.10.0)
Requires-Dist: click (==8.0.1)
